CHANGES.txt
CONTRIBUTORS.txt
MANIFEST.in
README.txt
setup.cfg
setup.py
docs/HISTORY.txt
docs/INSTALL.txt
docs/LICENSE.GPL
docs/LICENSE.txt
proteon/__init__.py
proteon.ExporterImporter.egg-info/PKG-INFO
proteon.ExporterImporter.egg-info/SOURCES.txt
proteon.ExporterImporter.egg-info/dependency_links.txt
proteon.ExporterImporter.egg-info/entry_points.txt
proteon.ExporterImporter.egg-info/namespace_packages.txt
proteon.ExporterImporter.egg-info/not-zip-safe
proteon.ExporterImporter.egg-info/paster_plugins.txt
proteon.ExporterImporter.egg-info/requires.txt
proteon.ExporterImporter.egg-info/top_level.txt
proteon/exporterimporter/README.txt
proteon/exporterimporter/__init__.py
proteon/exporterimporter/config.py
proteon/exporterimporter/configure.zcml
proteon/exporterimporter/setuphandlers.py
proteon/exporterimporter/tool.gif
proteon/exporterimporter/Extensions/Install.py
proteon/exporterimporter/browser/__init__.py
proteon/exporterimporter/browser/config.py
proteon/exporterimporter/browser/configure.zcml
proteon/exporterimporter/browser/images/import-icon.png
proteon/exporterimporter/content/__init__.py
proteon/exporterimporter/content/configure.zcml
proteon/exporterimporter/content/knmporm.py
proteon/exporterimporter/content/export/export_users.py
proteon/exporterimporter/content/importer/__init__.py
proteon/exporterimporter/content/importer/content_importer.py
proteon/exporterimporter/content/importer/import_users.py
proteon/exporterimporter/content/importer/mongerorm.py
proteon/exporterimporter/interfaces/__init__.py
proteon/exporterimporter/portlets/__init__.py
proteon/exporterimporter/portlets/configure.zcml
proteon/exporterimporter/profiles/default/actionicons.xml
proteon/exporterimporter/profiles/default/controlpanel.xml
proteon/exporterimporter/profiles/default/factorytool.xml
proteon/exporterimporter/profiles/default/metadata.xml
proteon/exporterimporter/profiles/default/portlets.xml
proteon/exporterimporter/profiles/default/proteon.exporterimporter_various.txt
proteon/exporterimporter/profiles/default/types.xml
proteon/exporterimporter/tests/__init__.py
proteon/exporterimporter/tests/base.py
proteon/exporterimporter/tests/test_doctest.py