Metadata-Version: 1.0
Name: proteon.ExporterImporter
Version: 0.1-alpha
Summary: UNKNOWN
Home-page: http://proteon.nl
Author: Horacio Duran
Author-email: hduran@machinalis.com
License: GPL
Platform: UNKNOWN
Classifier: Framework :: Plone
Classifier: Intended Audience :: Developers
Classifier: License :: OSI Approved :: GNU General Public License (GPL)
